django_lazy_gdal/__init__.py
django_lazy_gdal/apps.py
django_lazy_gdal/libgdal.py
django_lazy_gdal-0.2.2.dist-info/METADATA
django_lazy_gdal-0.2.2.dist-info/WHEEL
django_lazy_gdal-0.2.2.dist-info/licenses/AUTHORS.md
django_lazy_gdal-0.2.2.dist-info/licenses/LICENSE
django_lazy_gdal-0.2.2.dist-info/RECORD
