Metadata-Version: 2.4
Name: django-lazy-gdal
Version: 0.2.2
Summary: A Django app for patching `django.contrib.gis` to lazily load the GDAL library
Project-URL: Documentation, https://github.com/joshuadavidthomas/django-lazy-gdal#readme
Project-URL: Issues, https://github.com/joshuadavidthomas/django-lazy-gdal/issues
Project-URL: Source, https://github.com/joshuadavidthomas/django-lazy-gdal
Author-email: Josh Thomas <josh@joshthomas.dev>
License-File: AUTHORS.md
License-File: LICENSE
Classifier: Development Status :: 3 - Alpha
Classifier: Framework :: Django :: 4.2
Classifier: Framework :: Django :: 5.1
Classifier: Framework :: Django :: 5.2
Classifier: License :: OSI Approved :: MIT License
Classifier: Operating System :: OS Independent
Classifier: Programming Language :: Python
Classifier: Programming Language :: Python :: 3
Classifier: Programming Language :: Python :: 3 :: Only
Classifier: Programming Language :: Python :: 3.9
Classifier: Programming Language :: Python :: 3.10
Classifier: Programming Language :: Python :: 3.11
Classifier: Programming Language :: Python :: 3.12
Classifier: Programming Language :: Python :: 3.13
Classifier: Programming Language :: Python :: Implementation :: CPython
Requires-Python: >=3.9
Requires-Dist: django>=4.2
